CHANGES.rst
COPYING.txt
MANIFEST.in
README.rst
setup.py
rattail_fabric/__init__.py
rattail_fabric/_version.py
rattail_fabric/apache.py
rattail_fabric/apt.py
rattail_fabric/backup.py
rattail_fabric/borg.py
rattail_fabric/certbot.py
rattail_fabric/composer.py
rattail_fabric/core.py
rattail_fabric/corepos.py
rattail_fabric/ejabberd.py
rattail_fabric/freetds.py
rattail_fabric/kimai.py
rattail_fabric/luigi.py
rattail_fabric/mysql.py
rattail_fabric/pod.py
rattail_fabric/postfix.py
rattail_fabric/postgresql.py
rattail_fabric/python.py
rattail_fabric/rattail.py
rattail_fabric/shinken.py
rattail_fabric/soffice.py
rattail_fabric/ssh.py
rattail_fabric.egg-info/PKG-INFO
rattail_fabric.egg-info/SOURCES.txt
rattail_fabric.egg-info/dependency_links.txt
rattail_fabric.egg-info/not-zip-safe
rattail_fabric.egg-info/requires.txt
rattail_fabric.egg-info/top_level.txt